webtestpilot/__init__.py
webtestpilot/config.py
webtestpilot/config.yaml
webtestpilot/main.py
webtestpilot/baml_client/__init__.py
webtestpilot/baml_client/async_client.py
webtestpilot/baml_client/config.py
webtestpilot/baml_client/globals.py
webtestpilot/baml_client/inlinedbaml.py
webtestpilot/baml_client/parser.py
webtestpilot/baml_client/runtime.py
webtestpilot/baml_client/stream_types.py
webtestpilot/baml_client/sync_client.py
webtestpilot/baml_client/tracing.py
webtestpilot/baml_client/type_builder.py
webtestpilot/baml_client/type_map.py
webtestpilot/baml_client/types.py
webtestpilot/baml_client/watchers.py
webtestpilot/executor/__init__.py
webtestpilot/executor/mark.js
webtestpilot/executor/unmark.js
webtestpilot/executor/utils.py
webtestpilot/executor/assertion_api/__init__.py
webtestpilot/executor/assertion_api/element.py
webtestpilot/executor/assertion_api/pydantic_schema.py
webtestpilot/executor/assertion_api/session.py
webtestpilot/executor/assertion_api/state.py
webtestpilot/executor/assertion_api/type_utils.py
webtestpilot/executor/automators/__init__.py
webtestpilot/executor/page_reidentification/abstract.py
webtestpilot/executor/page_reidentification/accessibility.py
webtestpilot/executor/page_reidentification/distance.py
webtestpilot-0.1.12.dist-info/METADATA
webtestpilot-0.1.12.dist-info/WHEEL
webtestpilot-0.1.12.dist-info/top_level.txt
webtestpilot-0.1.12.dist-info/RECORD
