Metadata-Version: 2.4
Name: webtestpilot
Version: 0.1.12
Summary: WebTestPilot is an LLM-driven automated web testing framework for end-to-end browser testing.
Requires-Python: >=3.12
Requires-Dist: baml-py==0.214.0
Requires-Dist: openai>=1.95.1
Requires-Dist: pillow>=11.3.0
Requires-Dist: playwright>=1.53.0
Requires-Dist: pydantic>=2.11.7
Requires-Dist: pytest>=9.0.2
Requires-Dist: python-dotenv>=1.1.1
Requires-Dist: python-levenshtein>=0.27.1
Requires-Dist: pyyaml>=6.0.2
Requires-Dist: zss>=1.2.0
